[{"id":1,"title":"Animal","size":8,"content":["https:\/\/github.com\/truyenfull\/t_o_p_\/raw\/main\/bg_top\/animal\/AdobeStock_236222143.jpg","https:\/\/github.com\/truyenfull\/t_o_p_\/raw\/main\/bg_top\/animal\/AdobeStock_236222238.jpg","https:\/\/github.com\/truyenfull\/t_o_p_\/raw\/main\/bg_top\/animal\/AdobeStock_236240371.jpg","https:\/\/github.com\/truyenfull\/t_o_p_\/raw\/main\/bg_top\/animal\/AdobeStock_243621100.jpg","https:\/\/github.com\/truyenfull\/t_o_p_\/raw\/main\/bg_top\/animal\/AdobeStock_244683232.jpg","https:\/\/github.com\/truyenfull\/t_o_p_\/raw\/main\/bg_top\/animal\/AdobeStock_245068299.jpg","https:\/\/github.com\/truyenfull\/t_o_p_\/raw\/main\/bg_top\/animal\/AdobeStock_299104326.jpg","https:\/\/github.com\/truyenfull\/t_o_p_\/raw\/main\/bg_top\/animal\/AdobeStock_336914055.jpg"]},{"id":1,"title":"Nature","size":92,"content":["https:\/\/github.com\/truyenfull\/t_o_p_\/raw\/main\/bg_top\/nature\/AdobeStock_232016142.jpg","https:\/\/github.com\/truyenfull\/t_o_p_\/raw\/main\/bg_top\/nature\/AdobeStock_233159495.jpg","https:\/\/github.com\/truyenfull\/t_o_p_\/raw\/main\/bg_top\/nature\/AdobeStock_235581871.jpg","https:\/\/github.com\/truyenfull\/t_o_p_\/raw\/main\/bg_top\/nature\/AdobeStock_245289542.jpg","https:\/\/github.com\/truyenfull\/t_o_p_\/raw\/main\/bg_top\/nature\/AdobeStock_246072878.jpg","https:\/\/github.com\/truyenfull\/t_o_p_\/raw\/main\/bg_top\/nature\/AdobeStock_246522468.jpg","https:\/\/github.com\/truyenfull\/t_o_p_\/raw\/main\/bg_top\/nature\/AdobeStock_249959799.jpg","https:\/\/github.com\/truyenfull\/t_o_p_\/raw\/main\/bg_top\/nature\/AdobeStock_262913748.jpg","https:\/\/github.com\/truyenfull\/t_o_p_\/raw\/main\/bg_top\/nature\/AdobeStock_288540332.jpg","https:\/\/github.com\/truyenfull\/t_o_p_\/raw\/main\/bg_top\/nature\/AdobeStock_288542426.jpg","https:\/\/github.com\/truyenfull\/t_o_p_\/raw\/main\/bg_top\/nature\/AdobeStock_289757568.jpg","https:\/\/github.com\/truyenfull\/t_o_p_\/raw\/main\/bg_top\/nature\/AdobeStock_290183443.jpg","https:\/\/github.com\/truyenfull\/t_o_p_\/raw\/main\/bg_top\/nature\/AdobeStock_290186665.jpg","https:\/\/github.com\/truyenfull\/t_o_p_\/raw\/main\/bg_top\/nature\/AdobeStock_290870973.jpg","https:\/\/github.com\/truyenfull\/t_o_p_\/raw\/main\/bg_top\/nature\/AdobeStock_290877718.jpg","https:\/\/github.com\/truyenfull\/t_o_p_\/raw\/main\/bg_top\/nature\/AdobeStock_291404488.jpg","https:\/\/github.com\/truyenfull\/t_o_p_\/raw\/main\/bg_top\/nature\/AdobeStock_292015927.jpg","https:\/\/github.com\/truyenfull\/t_o_p_\/raw\/main\/bg_top\/nature\/AdobeStock_292106937.jpg","https:\/\/github.com\/truyenfull\/t_o_p_\/raw\/main\/bg_top\/nature\/AdobeStock_292197668.jpg","https:\/\/github.com\/truyenfull\/t_o_p_\/raw\/main\/bg_top\/nature\/AdobeStock_292203553.jpg","https:\/\/github.com\/truyenfull\/t_o_p_\/raw\/main\/bg_top\/nature\/AdobeStock_292803793.jpg","https:\/\/github.com\/truyenfull\/t_o_p_\/raw\/main\/bg_top\/nature\/AdobeStock_293310071.jpg","https:\/\/github.com\/truyenfull\/t_o_p_\/raw\/main\/bg_top\/nature\/AdobeStock_293345820.jpg","https:\/\/github.com\/truyenfull\/t_o_p_\/raw\/main\/bg_top\/nature\/AdobeStock_293661922.jpg","https:\/\/github.com\/truyenfull\/t_o_p_\/raw\/main\/bg_top\/nature\/AdobeStock_295572530.jpg","https:\/\/github.com\/truyenfull\/t_o_p_\/raw\/main\/bg_top\/nature\/AdobeStock_295704793.jpg","https:\/\/github.com\/truyenfull\/t_o_p_\/raw\/main\/bg_top\/nature\/AdobeStock_295786229.jpg","https:\/\/github.com\/truyenfull\/t_o_p_\/raw\/main\/bg_top\/nature\/AdobeStock_295798071.jpg","https:\/\/github.com\/truyenfull\/t_o_p_\/raw\/main\/bg_top\/nature\/AdobeStock_295881159.jpg","https:\/\/github.com\/truyenfull\/t_o_p_\/raw\/main\/bg_top\/nature\/AdobeStock_295890206.jpg","https:\/\/github.com\/truyenfull\/t_o_p_\/raw\/main\/bg_top\/nature\/AdobeStock_295964391.jpg","https:\/\/github.com\/truyenfull\/t_o_p_\/raw\/main\/bg_top\/nature\/AdobeStock_295970028.jpg","https:\/\/github.com\/truyenfull\/t_o_p_\/raw\/main\/bg_top\/nature\/AdobeStock_295978836.jpg","https:\/\/github.com\/truyenfull\/t_o_p_\/raw\/main\/bg_top\/nature\/AdobeStock_295980753.jpg","https:\/\/github.com\/truyenfull\/t_o_p_\/raw\/main\/bg_top\/nature\/AdobeStock_296707142.jpg","https:\/\/github.com\/truyenfull\/t_o_p_\/raw\/main\/bg_top\/nature\/AdobeStock_298574209.jpg","https:\/\/github.com\/truyenfull\/t_o_p_\/raw\/main\/bg_top\/nature\/AdobeStock_299382951.jpg","https:\/\/github.com\/truyenfull\/t_o_p_\/raw\/main\/bg_top\/nature\/AdobeStock_299432520.jpg","https:\/\/github.com\/truyenfull\/t_o_p_\/raw\/main\/bg_top\/nature\/AdobeStock_299677916.jpg","https:\/\/github.com\/truyenfull\/t_o_p_\/raw\/main\/bg_top\/nature\/AdobeStock_299739725.jpg","https:\/\/github.com\/truyenfull\/t_o_p_\/raw\/main\/bg_top\/nature\/AdobeStock_299772628.jpg","https:\/\/github.com\/truyenfull\/t_o_p_\/raw\/main\/bg_top\/nature\/AdobeStock_301830149.jpg","https:\/\/github.com\/truyenfull\/t_o_p_\/raw\/main\/bg_top\/nature\/AdobeStock_301830299.jpg","https:\/\/github.com\/truyenfull\/t_o_p_\/raw\/main\/bg_top\/nature\/AdobeStock_301830407.jpg","https:\/\/github.com\/truyenfull\/t_o_p_\/raw\/main\/bg_top\/nature\/AdobeStock_301846268.jpg","https:\/\/github.com\/truyenfull\/t_o_p_\/raw\/main\/bg_top\/nature\/AdobeStock_301859555.jpg","https:\/\/github.com\/truyenfull\/t_o_p_\/raw\/main\/bg_top\/nature\/AdobeStock_302152615.jpg","https:\/\/github.com\/truyenfull\/t_o_p_\/raw\/main\/bg_top\/nature\/AdobeStock_303676886.jpg","https:\/\/github.com\/truyenfull\/t_o_p_\/raw\/main\/bg_top\/nature\/AdobeStock_304772085.jpg","https:\/\/github.com\/truyenfull\/t_o_p_\/raw\/main\/bg_top\/nature\/AdobeStock_305086615.jpg","https:\/\/github.com\/truyenfull\/t_o_p_\/raw\/main\/bg_top\/nature\/AdobeStock_305090306.jpg","https:\/\/github.com\/truyenfull\/t_o_p_\/raw\/main\/bg_top\/nature\/AdobeStock_305104088.jpg","https:\/\/github.com\/truyenfull\/t_o_p_\/raw\/main\/bg_top\/nature\/AdobeStock_305104722.jpg","https:\/\/github.com\/truyenfull\/t_o_p_\/raw\/main\/bg_top\/nature\/AdobeStock_305105127.jpg","https:\/\/github.com\/truyenfull\/t_o_p_\/raw\/main\/bg_top\/nature\/AdobeStock_305114442.jpg","https:\/\/github.com\/truyenfull\/t_o_p_\/raw\/main\/bg_top\/nature\/AdobeStock_305569192.jpg","https:\/\/github.com\/truyenfull\/t_o_p_\/raw\/main\/bg_top\/nature\/AdobeStock_305893039.jpg","https:\/\/github.com\/truyenfull\/t_o_p_\/raw\/main\/bg_top\/nature\/AdobeStock_306944206.jpg","https:\/\/github.com\/truyenfull\/t_o_p_\/raw\/main\/bg_top\/nature\/AdobeStock_306944468.jpg","https:\/\/github.com\/truyenfull\/t_o_p_\/raw\/main\/bg_top\/nature\/AdobeStock_306945355.jpg","https:\/\/github.com\/truyenfull\/t_o_p_\/raw\/main\/bg_top\/nature\/AdobeStock_307580708.jpg","https:\/\/github.com\/truyenfull\/t_o_p_\/raw\/main\/bg_top\/nature\/AdobeStock_308341567.jpg","https:\/\/github.com\/truyenfull\/t_o_p_\/raw\/main\/bg_top\/nature\/AdobeStock_308494624.jpg","https:\/\/github.com\/truyenfull\/t_o_p_\/raw\/main\/bg_top\/nature\/AdobeStock_308742844.jpg","https:\/\/github.com\/truyenfull\/t_o_p_\/raw\/main\/bg_top\/nature\/AdobeStock_308743964.jpg","https:\/\/github.com\/truyenfull\/t_o_p_\/raw\/main\/bg_top\/nature\/AdobeStock_308744204.jpg","https:\/\/github.com\/truyenfull\/t_o_p_\/raw\/main\/bg_top\/nature\/AdobeStock_310007562.jpg","https:\/\/github.com\/truyenfull\/t_o_p_\/raw\/main\/bg_top\/nature\/AdobeStock_310602786.jpg","https:\/\/github.com\/truyenfull\/t_o_p_\/raw\/main\/bg_top\/nature\/AdobeStock_314617480.jpg","https:\/\/github.com\/truyenfull\/t_o_p_\/raw\/main\/bg_top\/nature\/AdobeStock_337256046.jpg","https:\/\/github.com\/truyenfull\/t_o_p_\/raw\/main\/bg_top\/nature\/AdobeStock_337582471.jpg","https:\/\/github.com\/truyenfull\/t_o_p_\/raw\/main\/bg_top\/nature\/AdobeStock_338151527.jpg","https:\/\/github.com\/truyenfull\/t_o_p_\/raw\/main\/bg_top\/nature\/AdobeStock_338160991.jpg","https:\/\/github.com\/truyenfull\/t_o_p_\/raw\/main\/bg_top\/nature\/AdobeStock_338168916.jpg","https:\/\/github.com\/truyenfull\/t_o_p_\/raw\/main\/bg_top\/nature\/AdobeStock_338171137.jpg","https:\/\/github.com\/truyenfull\/t_o_p_\/raw\/main\/bg_top\/nature\/AdobeStock_338172768.jpg","https:\/\/github.com\/truyenfull\/t_o_p_\/raw\/main\/bg_top\/nature\/AdobeStock_338172953.jpg","https:\/\/github.com\/truyenfull\/t_o_p_\/raw\/main\/bg_top\/nature\/AdobeStock_338175544.jpg","https:\/\/github.com\/truyenfull\/t_o_p_\/raw\/main\/bg_top\/nature\/AdobeStock_338766319.jpg","https:\/\/github.com\/truyenfull\/t_o_p_\/raw\/main\/bg_top\/nature\/AdobeStock_339074364.jpg","https:\/\/github.com\/truyenfull\/t_o_p_\/raw\/main\/bg_top\/nature\/AdobeStock_339832946.jpg","https:\/\/github.com\/truyenfull\/t_o_p_\/raw\/main\/bg_top\/nature\/AdobeStock_340745158.jpg","https:\/\/github.com\/truyenfull\/t_o_p_\/raw\/main\/bg_top\/nature\/AdobeStock_340850989.jpg","https:\/\/github.com\/truyenfull\/t_o_p_\/raw\/main\/bg_top\/nature\/AdobeStock_340882031.jpg","https:\/\/github.com\/truyenfull\/t_o_p_\/raw\/main\/bg_top\/nature\/AdobeStock_341152372.jpg","https:\/\/github.com\/truyenfull\/t_o_p_\/raw\/main\/bg_top\/nature\/AdobeStock_341152398.jpg","https:\/\/github.com\/truyenfull\/t_o_p_\/raw\/main\/bg_top\/nature\/AdobeStock_341153807.jpg","https:\/\/github.com\/truyenfull\/t_o_p_\/raw\/main\/bg_top\/nature\/AdobeStock_341153818.jpg","https:\/\/github.com\/truyenfull\/t_o_p_\/raw\/main\/bg_top\/nature\/AdobeStock_341173990.jpg","https:\/\/github.com\/truyenfull\/t_o_p_\/raw\/main\/bg_top\/nature\/AdobeStock_357734173.jpg","https:\/\/github.com\/truyenfull\/t_o_p_\/raw\/main\/bg_top\/nature\/AdobeStock_357734480.jpg","https:\/\/github.com\/truyenfull\/t_o_p_\/raw\/main\/bg_top\/nature\/AdobeStock_56345960.jpg"]}]